gas_dynamics/__about__.py
gas_dynamics/__init__.py
gas_dynamics/extra.py
gas_dynamics/fanno.py
gas_dynamics/fluids.py
gas_dynamics/prandtl_meyer.py
gas_dynamics/rayleigh.py
gas_dynamics/shocks.py
gas_dynamics/standard.py
gas_dynamics/design/__init__.py
gas_dynamics/design/design.py
gas_dynamics/fanno/__init__.py
gas_dynamics/fanno/fanno.py
gas_dynamics/prandtl_meyer/__init__.py
gas_dynamics/prandtl_meyer/prandtl_meyer.py
gas_dynamics/rayleigh/__init__.py
gas_dynamics/rayleigh/rayleigh.py
gas_dynamics/shocks/__init__.py
gas_dynamics/shocks/shocks.py
gas_dynamics/standard/__init__.py
gas_dynamics/standard/standard.py
gas_dynamics/tests/__init__.py
gas_dynamics/tests/testfile.py
tests/__init__.py
tests/test_fanno.py
tests/test_prandtl_meyer.py
tests/test_rayleigh.py
tests/test_shocks.py
tests/test_standard.py
gas_dynamics-0.4.2.dist-info/LICENSE.txt
gas_dynamics-0.4.2.dist-info/METADATA
gas_dynamics-0.4.2.dist-info/WHEEL
gas_dynamics-0.4.2.dist-info/top_level.txt
gas_dynamics-0.4.2.dist-info/RECORD
