Metadata-Version: 2.1
Name: gas-dynamics
Version: 0.4.2
Summary: Package containing functions for working with compressible flow
Home-page: UNKNOWN
Author: Fernando de la Fuente
Author-email: FernandoAdelaFuente@gmail.com
License: MIT
Project-URL: ReadtheDocs, http://gas-dynamics.readthedocs.io
Project-URL: Github, http://github.com/fernancode/gas_dynamics
Platform: UNKNOWN
Classifier: Development Status :: 3 - Alpha
Classifier: Programming Language :: Python :: 3.6
Classifier: Programming Language :: Python :: 3.7
Classifier: Programming Language :: Python :: 3.8
Classifier: License :: OSI Approved :: MIT License
Classifier: Operating System :: OS Independent
Requires-Python: >=3.6
Requires-Dist: numpy (==1.19.3)
Requires-Dist: scipy
Requires-Dist: matplotlib (==3.3.2)
